[
  {
    "filament_weight": 1000,
    "diameter": 1.75,
    "ean": "5905991403623",
    "article_number": "81295",
    "purchase_links": [
      {
        "store_id": "spectrum",
        "url": "https://shop.spectrumfilaments.com/product-eng-1838-Filament-Spectrum-ReFill-Pastello-PLA-1-75mm-FLAMINGO-RED-1kg.html"
      }
    ]
  },
  {
    "filament_weight": 1000,
    "diameter": 1.75,
    "ean": "5903175655196",
    "article_number": "80730",
    "purchase_links": [
      {
        "store_id": "spectrum",
        "url": "https://shop.spectrumfilaments.com/product-eng-1514-Filament-Pastello-PLA-1-75mm-FLAMINGO-RED-1kg.html"
      }
    ]
  }
]