[
  {
    "filament_weight": 1000,
    "diameter": 1.75,
    "ean": "5903175651594",
    "article_number": "80181",
    "purchase_links": [
      {
        "store_id": "80185",
        "url": "https://shop.spectrumfilaments.com/product-eng-1149-Filament-Spectrum-PLA-Glitter-1-75mm-STARDUST-BLUE-1kg.html",
        "affiliate": false
      }
    ]
  },
  {
    "filament_weight": 500,
    "diameter": 1.75,
    "ean": "5903175651600",
    "article_number": "80182",
    "purchase_links": [
      {
        "store_id": "spectrum",
        "url": "https://shop.spectrumfilaments.com/product-eng-1153-Filament-Spectrum-PLA-Glitter-1-75mm-STARDUST-BLUE-0-5kg.html",
        "affiliate": false
      }
    ]
  }
]