[
  {
    "filament_weight": 1000,
    "diameter": 1.75,
    "ean": "5903175651372",
    "article_number": "80162",
    "purchase_links": [
      {
        "store_id": "spectrum",
        "url": "https://shop.spectrumfilaments.com/product-eng-669-Filament-Spectrum-PLA-Glitter-1-75mm-VOLCANO-GREY-1kg.html"
      }
    ]
  },
  {
    "filament_weight": 500,
    "diameter": 1.75,
    "ean": "5903175651389",
    "article_number": "80163",
    "purchase_links": [
      {
        "store_id": "spectrum",
        "url": "https://shop.spectrumfilaments.com/product-eng-670-Filament-Spectrum-PLA-Glitter-1-75mm-VOLCANO-GREY-0-50kg.html"
      }
    ]
  }
]